elodin-0.15.5.dist-info/METADATA
elodin-0.15.5.dist-info/WHEEL
elodin-0.15.5.dist-info/entry_points.txt
elodin.libs/libgfortran-3ec47101.so.5
elodin.libs/libpython3-ddcf3302.10.so.1.0
elodin.libs/libquadmath-67d31475.so.0
elodin/FSW Workshop 2025 abstract.md
elodin/__init__.py
elodin/egm08.py
elodin/elodin.abi3.so
elodin/elodin.pyi
elodin/j2.py
elodin/jaxsim.py
elodin/py.typed
elodin-0.15.5.dist-info/RECORD
