Metadata-Version: 2.4
Name: elodin
Version: 0.15.5
Classifier: Programming Language :: Rust
Classifier: Programming Language :: Python :: Implementation :: CPython
Classifier: Programming Language :: Python :: Implementation :: PyPy
Requires-Dist: jax==0.4.31
Requires-Dist: numpy
Requires-Dist: typing-extensions
Requires-Dist: polars
Requires-Dist: pytest
Requires-Dist: matplotlib
Requires-Dist: pytest ; extra == 'tests'
Provides-Extra: tests
Provides-Extra: dynamic
Requires-Python: >=3.10, <3.13
